moboff.py
MobOff-0.2.3.dist-info/DESCRIPTION.rst
MobOff-0.2.3.dist-info/METADATA
MobOff-0.2.3.dist-info/RECORD
MobOff-0.2.3.dist-info/WHEEL
MobOff-0.2.3.dist-info/entry_points.txt
MobOff-0.2.3.dist-info/metadata.json
MobOff-0.2.3.dist-info/top_level.txt
