Metadata-Version: 2.0
Name: MobOff
Version: 0.2.3
Summary: Download youtube music and send to devices
Home-page: https://github.com/parth-vader/MobOff
Author: Parth Verma
Author-email: vermaparth97@gmail.com
License: MIT License
Download-URL: https://codeload.github.com/Parth-Vader/MobOff/tar.gz/0.2.2
Platform: UNKNOWN
Requires-Dist: pushbullet.py
Requires-Dist: youtube-dl
Requires-Dist: Click
